zc.zodbrecipes-3.1-py3.11-nspkg.pth
zc/zodbrecipes/__init__.py
zc/zodbrecipes/tests.py
zc/zodbrecipes/zeo.txt
zc.zodbrecipes-3.1.dist-info/METADATA
zc.zodbrecipes-3.1.dist-info/WHEEL
zc.zodbrecipes-3.1.dist-info/entry_points.txt
zc.zodbrecipes-3.1.dist-info/namespace_packages.txt
zc.zodbrecipes-3.1.dist-info/top_level.txt
zc.zodbrecipes-3.1.dist-info/RECORD
