Metadata-Version: 2.1
Name: zc.zodbrecipes
Version: 3.1
Summary: ZC Buildout recipes for ZODB
Home-page: https://github.com/zopefoundation/zc.zodbrecipes
Author: Jim Fulton
Author-email: jim@zope.com
License: ZPL 2.1
Keywords: zodb buildout
Classifier: Natural Language :: English
Classifier: Programming Language :: Python :: 3
Classifier: Programming Language :: Python :: 3.8
Classifier: Programming Language :: Python :: 3.9
Classifier: Programming Language :: Python :: 3.10
Classifier: Programming Language :: Python :: 3.11
Classifier: Programming Language :: Python :: 3.12
Classifier: Programming Language :: Python :: 3.13
Classifier: Programming Language :: Python :: Implementation :: CPython
Classifier: Programming Language :: Python :: Implementation :: PyPy
Classifier: Programming Language :: Python
Classifier: Framework :: Buildout
Classifier: Intended Audience :: Developers
Classifier: License :: OSI Approved :: Zope Public License
Classifier: Topic :: Software Development :: Build Tools
Classifier: Topic :: Software Development :: Libraries :: Python Modules
Requires-Python: >=3.8
Requires-Dist: zc.buildout
Requires-Dist: setuptools
Requires-Dist: zc.recipe.egg
Requires-Dist: ZConfig >=2.4
Provides-Extra: test
Requires-Dist: zdaemon ; extra == 'test'
Requires-Dist: ZEO ; extra == 'test'
Requires-Dist: zope.event ; extra == 'test'
Requires-Dist: zope.testing ; extra == 'test'
Requires-Dist: zope.proxy ; extra == 'test'
Requires-Dist: zope.testrunner ; extra == 'test'
Requires-Dist: zodbpickle ; extra == 'test'
